{
  "metadata": {
    "source": "https://www.hud.gov/sites/dfiles/PIH/documents/2024-HUD-VASH-Awards_List-by-PHA.pdf",
    "notice": "PIH 2024-18",
    "total_vouchers": 3518,
    "total_budget": 40071481,
    "extracted_date": "2026-01-18"
  },
  "awards": [
    {"pha_code": "AL002", "pha_name": "Mobile Housing Authority", "vamc": "V16/Gulf Coast HCS", "vouchers": 65, "budget": 451838},
    {"pha_code": "AR006", "pha_name": "Housing Authority of the City of Conway", "vamc": "V16/Central Arkansas HCS", "vouchers": 5, "budget": 25462},
    {"pha_code": "AR031", "pha_name": "Housing Authority of the City of Hot Springs", "vamc": "V16/Central Arkansas HCS", "vouchers": 5, "budget": 31897},
    {"pha_code": "AR170", "pha_name": "Jacksonville Housing Authority", "vamc": "V16/Central Arkansas HCS", "vouchers": 10, "budget": 69270},
    {"pha_code": "AZ001", "pha_name": "City of Phoenix Housing Department", "vamc": "V22/Phoenix", "vouchers": 100, "budget": 1293060},
    {"pha_code": "AZ003", "pha_name": "Glendale Housing Authority", "vamc": "V22/Phoenix", "vouchers": 15, "budget": 188879},
    {"pha_code": "AZ004", "pha_name": "City of Tucson", "vamc": "V22/Southern Arizona HCS", "vouchers": 20, "budget": 171233},
    {"pha_code": "AZ005", "pha_name": "City of Mesa Housing Authority", "vamc": "V22/Phoenix", "vouchers": 15, "budget": 185609},
    {"pha_code": "AZ010", "pha_name": "Pinal County Housing Authority", "vamc": "V22/Southern Arizona HCS", "vouchers": 40, "budget": 404261},
    {"pha_code": "AZ028", "pha_name": "City of Chandler", "vamc": "V22/Phoenix", "vouchers": 10, "budget": 168816},
    {"pha_code": "AZ032", "pha_name": "Scottsdale Housing Agency", "vamc": "V22/Phoenix", "vouchers": 10, "budget": 143326},
    {"pha_code": "CA004", "pha_name": "Housing Authority of the City of Los Angeles", "vamc": "V22/Greater Los Angeles HCS", "vouchers": 250, "budget": 3886200},
    {"pha_code": "CA007", "pha_name": "County of Sacramento Housing Authority", "vamc": "V21/Northern California HCS", "vouchers": 30, "budget": 404676},
    {"pha_code": "CA014", "pha_name": "Housing Authority of the County of San Mateo", "vamc": "V21/Palo Alto", "vouchers": 35, "budget": 815791},
    {"pha_code": "CA019", "pha_name": "Housing Authority of the County of San Bernadino", "vamc": "V22/Loma Linda HCS", "vouchers": 75, "budget": 1140795},
    {"pha_code": "CA024", "pha_name": "Housing Authority of San Joaquin", "vamc": "V21/Northern California HCS", "vouchers": 10, "budget": 91739},
    {"pha_code": "CA043", "pha_name": "Housing Authority of the County of Butte", "vamc": "V21/Northern California HCS", "vouchers": 20, "budget": 160488},
    {"pha_code": "CA044", "pha_name": "Housing Authority of the County of Yolo", "vamc": "V21/Northern California HCS", "vouchers": 20, "budget": 256466},
    {"pha_code": "CA063", "pha_name": "San Diego Housing Commission", "vamc": "V22/San Diego HCS", "vouchers": 75, "budget": 1447938},
    {"pha_code": "CA066", "pha_name": "Suisun City Housing Authority", "vamc": "V21/Northern California HCS", "vouchers": 5, "budget": 91219},
    {"pha_code": "CA072", "pha_name": "Housing Authority of the County of Santa Cruz", "vamc": "V21/Palo Alto", "vouchers": 20, "budget": 417583},
    {"pha_code": "CA073", "pha_name": "Housing Authority of the City of Napa", "vamc": "V21/Northern California HCS", "vouchers": 15, "budget": 272776},
    {"pha_code": "CA074", "pha_name": "Housing Authority of the City of Livermore", "vamc": "V21/Palo Alto", "vouchers": 8, "budget": 155717},
    {"pha_code": "CA082", "pha_name": "Inglewood Housing Authority", "vamc": "V22/Greater Los Angeles HCS", "vouchers": 35, "budget": 468514},
    {"pha_code": "CA085", "pha_name": "Sonoma County Housing Authority", "vamc": "V21/San Francisco", "vouchers": 10, "budget": 146866},
    {"pha_code": "CA094", "pha_name": "Orange County Housing Authority", "vamc": "V22/Long Beach HCS", "vouchers": 50, "budget": 961170},
    {"pha_code": "CA106", "pha_name": "Housing Authority of the City of Redding", "vamc": "V21/Northern California HCS", "vouchers": 15, "budget": 92351},
    {"pha_code": "CA108", "pha_name": "Housing Authority of the County of San Diego", "vamc": "V22/San Diego HCS", "vouchers": 50, "budget": 1126776},
    {"pha_code": "CA123", "pha_name": "City of Pomona Housing Authority", "vamc": "V22/Greater Los Angeles HCS", "vouchers": 30, "budget": 500872},
    {"pha_code": "CA144", "pha_name": "Lake County Housing Commission", "vamc": "V21/San Francisco", "vouchers": 5, "budget": 53276},
    {"pha_code": "CO001", "pha_name": "Housing Authority of the City and County of Denver", "vamc": "V19/Eastern Colorado HCS", "vouchers": 25, "budget": 370710},
    {"pha_code": "CO041", "pha_name": "Housing Catalyst", "vamc": "V19/Cheyenne", "vouchers": 10, "budget": 111018},
    {"pha_code": "CO061", "pha_name": "Boulder County Housing Authority", "vamc": "V19/Eastern Colorado HCS", "vouchers": 10, "budget": 163231},
    {"pha_code": "CO911", "pha_name": "Colorado Division of Housing", "vamc": "V19/Eastern Colorado HCS", "vouchers": 50, "budget": 629586},
    {"pha_code": "FL002", "pha_name": "Housing Authority of the City of St. Petersburg", "vamc": "V08/Bay Pines", "vouchers": 35, "budget": 424448},
    {"pha_code": "FL018", "pha_name": "Panama City Housing Authority", "vamc": "V16/Gulf Coast HCS", "vouchers": 10, "budget": 83282},
    {"pha_code": "FL025", "pha_name": "Housing Authority of the City of Titusville", "vamc": "V08/Orlando", "vouchers": 25, "budget": 231447},
    {"pha_code": "FL033", "pha_name": "Seminole County Housing Authority", "vamc": "V08/Orlando", "vouchers": 8, "budget": 106491},
    {"pha_code": "FL062", "pha_name": "Pinellas County Housing Authority", "vamc": "V08/Bay Pines", "vouchers": 35, "budget": 423007},
    {"pha_code": "FL066", "pha_name": "Hialeah Housing Authority", "vamc": "V08/Miami", "vouchers": 30, "budget": 509026},
    {"pha_code": "FL068", "pha_name": "Housing Authority of the City of Homestead", "vamc": "V08/Miami", "vouchers": 30, "budget": 467006},
    {"pha_code": "FL075", "pha_name": "Clearwater Housing Authority", "vamc": "V08/Bay Pines", "vouchers": 10, "budget": 161804},
    {"pha_code": "FL079", "pha_name": "Broward County Housing Authority", "vamc": "V08/Miami", "vouchers": 68, "budget": 953928},
    {"pha_code": "FL083", "pha_name": "Delray Beach Housing Authority", "vamc": "V08/West Palm Beach", "vouchers": 5, "budget": 93175},
    {"pha_code": "FL106", "pha_name": "Lake County Housing Authority", "vamc": "V08/Orlando", "vouchers": 5, "budget": 67502},
    {"pha_code": "FL137", "pha_name": "Hernando County Housing Authority", "vamc": "V08/Tampa", "vouchers": 5, "budget": 49995},
    {"pha_code": "FL147", "pha_name": "Citrus County Housing Services", "vamc": "V08/Tampa", "vouchers": 10, "budget": 66132},
    {"pha_code": "FL201", "pha_name": "Osceola County Housing and Community Services", "vamc": "V08/Orlando", "vouchers": 8, "budget": 85552},
    {"pha_code": "GA006", "pha_name": "Housing Authority of the City of Atlanta", "vamc": "V07/Atlanta", "vouchers": 25, "budget": 314034},
    {"pha_code": "GA078", "pha_name": "East Point Housing Authority", "vamc": "V07/Atlanta", "vouchers": 25, "budget": 258867},
    {"pha_code": "GQ901", "pha_name": "Guam Housing and Urban Renewal Authority", "vamc": "V21/Pacific Islands HCS", "vouchers": 24, "budget": 324605},
    {"pha_code": "HI002", "pha_name": "County of Hawaii Office of Housing and Community Development", "vamc": "V21/Pacific Islands HCS", "vouchers": 46, "budget": 527326},
    {"pha_code": "HI003", "pha_name": "City and County of Honolulu", "vamc": "V21/Pacific Islands HCS", "vouchers": 5, "budget": 74702},
    {"pha_code": "HI004", "pha_name": "County of Maui Department of Housing", "vamc": "V21/Pacific Islands HCS", "vouchers": 30, "budget": 434286},
    {"pha_code": "IA020", "pha_name": "Des Moines Municipal Housing Agency", "vamc": "V23/Omaha", "vouchers": 20, "budget": 110230},
    {"pha_code": "ID016", "pha_name": "Southwestern Idaho Cooperative Housing Authority", "vamc": "V20/Boise", "vouchers": 25, "budget": 237543},
    {"pha_code": "IN003", "pha_name": "Housing Authority of the City of Fort Wayne", "vamc": "V10/Northern Indiana HCS", "vouchers": 5, "budget": 32835},
    {"pha_code": "IN901", "pha_name": "Indiana Housing and Community Development Authority", "vamc": "V10/Cincinnati", "vouchers": 5, "budget": 37667},
    {"pha_code": "KS002", "pha_name": "Topeka Housing Authority", "vamc": "V15/Eastern Kansas HCS", "vouchers": 25, "budget": 109029},
    {"pha_code": "KS063", "pha_name": "Manhattan Housing Authority", "vamc": "V15/Eastern Kansas HCS", "vouchers": 8, "budget": 48132},
    {"pha_code": "KS068", "pha_name": "Leavenworth Housing Authority", "vamc": "V15/Eastern Kansas HCS", "vouchers": 15, "budget": 88727},
    {"pha_code": "KY061", "pha_name": "Housing Authority of Georgetown", "vamc": "V09/Lexington", "vouchers": 5, "budget": 35964},
    {"pha_code": "KY132", "pha_name": "City of Richmond Section 8 Housing", "vamc": "V09/Lexington", "vouchers": 25, "budget": 146091},
    {"pha_code": "KY161", "pha_name": "Appalachian Foothills Housing Agency, Inc.", "vamc": "V05/Huntington", "vouchers": 5, "budget": 33295},
    {"pha_code": "LA190", "pha_name": "Bossier Parish Section 8 Housing Authority", "vamc": "V16/Overton Brooks", "vouchers": 20, "budget": 118498},
    {"pha_code": "LA903", "pha_name": "Louisiana Housing Authority", "vamc": "V16/Alexandria", "vouchers": 10, "budget": 61663},
    {"pha_code": "MI058", "pha_name": "Lansing Housing Commission", "vamc": "V10/Battle Creek", "vouchers": 23, "budget": 160326},
    {"pha_code": "MI064", "pha_name": "Ann Arbor Housing Commission", "vamc": "V10/Ann Arbor HCS", "vouchers": 41, "budget": 436773},
    {"pha_code": "MI901", "pha_name": "Michigan State Housing Development Authority", "vamc": "V10/Battle Creek", "vouchers": 43, "budget": 325952},
    {"pha_code": "MI901", "pha_name": "Michigan State Housing Development Authority", "vamc": "V10/Detroit", "vouchers": 40, "budget": 303211},
    {"pha_code": "MI901", "pha_name": "Michigan State Housing Development Authority", "vamc": "V10/Saginaw", "vouchers": 5, "budget": 37901},
    {"pha_code": "MI901", "pha_name": "Michigan State Housing Development Authority", "vamc": "V12/Iron Mountain MI", "vouchers": 5, "budget": 37901},
    {"pha_code": "MN003", "pha_name": "Housing and Redevelopment Authority of Duluth, Minnesota", "vamc": "V23/Minneapolis HCS", "vouchers": 7, "budget": 53692},
    {"pha_code": "MO004", "pha_name": "Housing Authority of St. Louis County", "vamc": "V15/St Louis", "vouchers": 40, "budget": 318269},
    {"pha_code": "MO006", "pha_name": "Housing Authority of St. Charles", "vamc": "V15/St Louis", "vouchers": 5, "budget": 38813},
    {"pha_code": "MO007", "pha_name": "Columbia Housing Authority", "vamc": "V15/Columbia MO", "vouchers": 28, "budget": 172274},
    {"pha_code": "MO205", "pha_name": "Franklin County Housing Authority", "vamc": "V15/St Louis", "vouchers": 5, "budget": 26776},
    {"pha_code": "NC009", "pha_name": "Fayetteville Metropolitan Housing Authority", "vamc": "V06/Fayetteville NC", "vouchers": 40, "budget": 314021},
    {"pha_code": "NC011", "pha_name": "Greensboro Housing Authority", "vamc": "V06/Salisbury", "vouchers": 30, "budget": 166738},
    {"pha_code": "NC020", "pha_name": "Housing Authority of the City of Wilson", "vamc": "V06/Durham", "vouchers": 5, "budget": 31414},
    {"pha_code": "NC141", "pha_name": "Coastal Community Action", "vamc": "V06/Durham", "vouchers": 5, "budget": 26905},
    {"pha_code": "NC144", "pha_name": "Eastern Carolina Human Services Agency, Inc", "vamc": "V06/Fayetteville NC", "vouchers": 10, "budget": 75008},
    {"pha_code": "NC159", "pha_name": "Western Piedmont Council of Governments", "vamc": "V06/Asheville-Oteen", "vouchers": 10, "budget": 60871},
    {"pha_code": "NC161", "pha_name": "Isothermal Planning and Development Commission dba Foothills Regional Commission", "vamc": "V06/Asheville-Oteen", "vouchers": 5, "budget": 27780},
    {"pha_code": "NJ008", "pha_name": "City of Long Branch Housing Authority", "vamc": "V02/New Jersey HCS", "vouchers": 10, "budget": 128092},
    {"pha_code": "NJ113", "pha_name": "Union County Housing Authority", "vamc": "V02/New Jersey HCS", "vouchers": 22, "budget": 309458},
    {"pha_code": "NJ204", "pha_name": "Housing Authority of Gloucester County", "vamc": "V04/Philadelphia", "vouchers": 40, "budget": 452069},
    {"pha_code": "NJ912", "pha_name": "New Jersey Department of Community Affairs", "vamc": "V02/New Jersey HCS", "vouchers": 50, "budget": 626214},
    {"pha_code": "NJ912", "pha_name": "New Jersey Department of Community Affairs", "vamc": "V04/Philadelphia", "vouchers": 20, "budget": 250486},
    {"pha_code": "NM001", "pha_name": "Albuquerque Housing Authority", "vamc": "V22/New Mexico HCS", "vouchers": 77, "budget": 539200},
    {"pha_code": "NM003", "pha_name": "Mesilla Valley Public Housing Authority", "vamc": "V17/El Paso HCS", "vouchers": 10, "budget": 59243},
    {"pha_code": "NM057", "pha_name": "Bernalillo County Housing Authority", "vamc": "V22/New Mexico HCS", "vouchers": 50, "budget": 411618},
    {"pha_code": "NV001", "pha_name": "Housing Authority of the City of Reno", "vamc": "V21/Sierra Nevada HCS", "vouchers": 52, "budget": 447445},
    {"pha_code": "NV018", "pha_name": "Southern Nevada Regional Housing Authority", "vamc": "V21/Southern Nevada HCS", "vouchers": 99, "budget": 1022642},
    {"pha_code": "NY005", "pha_name": "New York City Housing Authority", "vamc": "V02/Bronx", "vouchers": 25, "budget": 351636},
    {"pha_code": "NY005", "pha_name": "New York City Housing Authority", "vamc": "V02/New York Harbor HCS", "vouchers": 30, "budget": 421963},
    {"pha_code": "NY079", "pha_name": "City of Glens Falls Housing Authority", "vamc": "V02/Albany", "vouchers": 15, "budget": 101660},
    {"pha_code": "NY110", "pha_name": "NYC Dept of Housing Preservation and Development", "vamc": "V02/Bronx", "vouchers": 8, "budget": 119667},
    {"pha_code": "NY904", "pha_name": "NYS Housing Trust Fund Corporation", "vamc": "V03/Northport", "vouchers": 83, "budget": 1187232},
    {"pha_code": "OH001", "pha_name": "Columbus Metropolitan Housing Authority", "vamc": "V10/Columbus", "vouchers": 15, "budget": 126403},
    {"pha_code": "OH002", "pha_name": "Youngstown Metropolitan Housing Authority", "vamc": "V10/Cleveland", "vouchers": 5, "budget": 21743},
    {"pha_code": "OH003", "pha_name": "Cuyahoga Metropolitan Housing Authority", "vamc": "V10/Cleveland", "vouchers": 5, "budget": 36800},
    {"pha_code": "OH007", "pha_name": "Akron Metropolitan Housing Authority", "vamc": "V10/Cleveland", "vouchers": 5, "budget": 30025},
    {"pha_code": "OH008", "pha_name": "Trumbull Metropolitan Housing Authority", "vamc": "V10/Cleveland", "vouchers": 5, "budget": 23934},
    {"pha_code": "OH012", "pha_name": "Lorain Metropolitan Housing Authority", "vamc": "V10/Cleveland", "vouchers": 5, "budget": 38273},
    {"pha_code": "OH026", "pha_name": "Columbiana Metropolitan Housing Authority", "vamc": "V10/Cleveland", "vouchers": 5, "budget": 22950},
    {"pha_code": "OH027", "pha_name": "Medina Metropolitan Housing Authority", "vamc": "V10/Cleveland", "vouchers": 5, "budget": 40646},
    {"pha_code": "OH028", "pha_name": "Erie Metropolitan Housing Authority", "vamc": "V10/Cleveland", "vouchers": 5, "budget": 28740},
    {"pha_code": "OH043", "pha_name": "Licking Metropolitan Housing Authority", "vamc": "V10/Columbus", "vouchers": 30, "budget": 238730},
    {"pha_code": "OK002", "pha_name": "Oklahoma City Housing Authority", "vamc": "V19/Oklahoma City", "vouchers": 50, "budget": 360078},
    {"pha_code": "OK005", "pha_name": "Lawton Housing Authority", "vamc": "V19/Oklahoma City", "vouchers": 10, "budget": 63690},
    {"pha_code": "OK139", "pha_name": "Housing Authority of the City of Norman", "vamc": "V19/Oklahoma City", "vouchers": 5, "budget": 35458},
    {"pha_code": "OK901", "pha_name": "Oklahoma Housing Finance Agency", "vamc": "V19/Muskogee", "vouchers": 34, "budget": 238953},
    {"pha_code": "OK901", "pha_name": "Oklahoma Housing Finance Agency", "vamc": "V19/Oklahoma City", "vouchers": 15, "budget": 105421},
    {"pha_code": "OR001", "pha_name": "Housing Authority of Clackamas County", "vamc": "V20/Portland", "vouchers": 25, "budget": 321675},
    {"pha_code": "OR005", "pha_name": "Housing Authority of Lincoln County", "vamc": "V20/Portland", "vouchers": 5, "budget": 39216},
    {"pha_code": "OR008", "pha_name": "Housing and Urban Renewal Agency of Polk County dba West Valley Housing Authority", "vamc": "V20/Portland", "vouchers": 5, "budget": 39660},
    {"pha_code": "OR011", "pha_name": "Housing Authority of the City of Salem", "vamc": "V20/Portland", "vouchers": 25, "budget": 233001},
    {"pha_code": "OR014", "pha_name": "Marion County Housing Authority", "vamc": "V20/Portland", "vouchers": 5, "budget": 57656},
    {"pha_code": "OR022", "pha_name": "Housing Authority of Washington County", "vamc": "V20/Portland", "vouchers": 50, "budget": 615090},
    {"pha_code": "OR028", "pha_name": "Northwest Oregon Housing Authority", "vamc": "V20/Portland", "vouchers": 10, "budget": 103535},
    {"pha_code": "OR034", "pha_name": "Central Oregon Regional Housing Authority dba Housing Works", "vamc": "V20/Portland", "vouchers": 5, "budget": 39234},
    {"pha_code": "PA002", "pha_name": "Philadelphia Housing Authority", "vamc": "V04/Philadelphia", "vouchers": 20, "budget": 197045},
    {"pha_code": "PA006", "pha_name": "Allegheny County Housing Authority", "vamc": "V04/Pittsburgh HCS", "vouchers": 10, "budget": 82872},
    {"pha_code": "PA012", "pha_name": "Montgomery County Housing Authority", "vamc": "V04/Coatesville", "vouchers": 5, "budget": 63319},
    {"pha_code": "PA024", "pha_name": "Easton Housing Authority", "vamc": "V04/Wilkes Barre", "vouchers": 15, "budget": 195538},
    {"pha_code": "PA035", "pha_name": "Housing Authority of the County of Dauphin", "vamc": "V04/Lebanon", "vouchers": 25, "budget": 261153},
    {"pha_code": "PA046", "pha_name": "Housing Authority of Chester County", "vamc": "V04/Coatesville", "vouchers": 5, "budget": 57403},
    {"pha_code": "PA047", "pha_name": "Wilkes-Barre Housing Authority", "vamc": "V04/Wilkes Barre", "vouchers": 10, "budget": 72167},
    {"pha_code": "PA071", "pha_name": "Berks County Housing Authority", "vamc": "V04/Lebanon", "vouchers": 14, "budget": 98078},
    {"pha_code": "PA076", "pha_name": "Northhampton County Housing Authority", "vamc": "V04/Wilkes Barre", "vouchers": 8, "budget": 87257},
    {"pha_code": "SC004", "pha_name": "Greenville Housing Authority", "vamc": "V07/Columbia SC", "vouchers": 50, "budget": 392610},
    {"pha_code": "SC034", "pha_name": "Housing Authority of Myrtle Beach", "vamc": "V07/Charleston", "vouchers": 25, "budget": 243225},
    {"pha_code": "TN007", "pha_name": "Jackson Housing Authority", "vamc": "V09/Memphis", "vouchers": 6, "budget": 48126},
    {"pha_code": "TX004", "pha_name": "Fort Worth Housing Solutions", "vamc": "V17/Dallas", "vouchers": 10, "budget": 95518},
    {"pha_code": "TX006", "pha_name": "Opportunity Home San Antonio", "vamc": "V17/San Antonio", "vouchers": 10, "budget": 74780},
    {"pha_code": "TX010", "pha_name": "Waco Housing Authority", "vamc": "V17/Temple", "vouchers": 15, "budget": 103320},
    {"pha_code": "TX431", "pha_name": "Tarrant County Housing Assistance Office", "vamc": "V17/Dallas", "vouchers": 30, "budget": 295481},
    {"pha_code": "TX432", "pha_name": "El Passo County Housing Authority", "vamc": "V17/El Paso HCS", "vouchers": 10, "budget": 62296},
    {"pha_code": "TX452", "pha_name": "Housing Authority of Bexar County", "vamc": "V17/San Antonio", "vouchers": 50, "budget": 414702},
    {"pha_code": "TX455", "pha_name": "Odessa Housing Authority", "vamc": "V17/West Texas HCS", "vouchers": 5, "budget": 35630},
    {"pha_code": "TX457", "pha_name": "City of Marshall Housing Authority", "vamc": "V16/Overton Brooks", "vouchers": 5, "budget": 37430},
    {"pha_code": "TX485", "pha_name": "Housing Authority of the City of Big Springs, TX", "vamc": "V17/West Texas HCS", "vouchers": 5, "budget": 33918},
    {"pha_code": "TX534", "pha_name": "Midland County Housing Authority", "vamc": "V17/West Texas HCS", "vouchers": 5, "budget": 51004},
    {"pha_code": "TX901", "pha_name": "Texas Department of Housing and Community Affairs", "vamc": "V16/Houston", "vouchers": 15, "budget": 134680},
    {"pha_code": "TX901", "pha_name": "Texas Department of Housing and Community Affairs", "vamc": "V17/San Antonio", "vouchers": 10, "budget": 89786},
    {"pha_code": "VA011", "pha_name": "City of Roanoke Redevelopment and Housing Authority", "vamc": "V06/Salem", "vouchers": 5, "budget": 34942},
    {"pha_code": "VA023", "pha_name": "Staunton Redevelopment and Housing Authority", "vamc": "V06/Salem", "vouchers": 5, "budget": 41335},
    {"pha_code": "VA901", "pha_name": "Virginia Housing Redevelopment Authority", "vamc": "V06/Richmond", "vouchers": 25, "budget": 269343},
    {"pha_code": "WA008", "pha_name": "Vancouver Housing Authority", "vamc": "V20/Portland", "vouchers": 50, "budget": 618084},
    {"pha_code": "WA012", "pha_name": "Housing Authority City of Kennewick", "vamc": "V20/Walla Walla", "vouchers": 15, "budget": 139984},
    {"pha_code": "WA025", "pha_name": "Housing Authority of the City of Bellingham", "vamc": "V20/Seattle", "vouchers": 10, "budget": 96763},
    {"pha_code": "WV037", "pha_name": "Housing Authority of Mingo County", "vamc": "V05/Huntington", "vouchers": 23, "budget": 123833}
  ]
}
